CHANGES
TODO.txt
bootstrap.py
buildout.cfg
setup.py
iw/__init__.py
iw.recipe.subversion.egg-info/PKG-INFO
iw.recipe.subversion.egg-info/SOURCES.txt
iw.recipe.subversion.egg-info/dependency_links.txt
iw.recipe.subversion.egg-info/entry_points.txt
iw.recipe.subversion.egg-info/namespace_packages.txt
iw.recipe.subversion.egg-info/not-zip-safe
iw.recipe.subversion.egg-info/requires.txt
iw.recipe.subversion.egg-info/top_level.txt
iw/recipe/__init__.py
iw/recipe/subversion/README.txt
iw/recipe/subversion/__init__.py
iw/recipe/subversion/tests/__init__.py
iw/recipe/subversion/tests/test_subversiondocs.py
iw/recipe/subversion/tests/repos/README.txt
iw/recipe/subversion/tests/repos/format
iw/recipe/subversion/tests/repos/conf/authz
iw/recipe/subversion/tests/repos/conf/passwd
iw/recipe/subversion/tests/repos/conf/svnserve.conf
iw/recipe/subversion/tests/repos/db/current
iw/recipe/subversion/tests/repos/db/format
iw/recipe/subversion/tests/repos/db/fs-type
iw/recipe/subversion/tests/repos/db/uuid
iw/recipe/subversion/tests/repos/db/write-lock
iw/recipe/subversion/tests/repos/db/revprops/0
iw/recipe/subversion/tests/repos/db/revprops/1
iw/recipe/subversion/tests/repos/db/revprops/2
iw/recipe/subversion/tests/repos/db/revprops/3
iw/recipe/subversion/tests/repos/db/revprops/4
iw/recipe/subversion/tests/repos/db/revs/0
iw/recipe/subversion/tests/repos/db/revs/1
iw/recipe/subversion/tests/repos/db/revs/2
iw/recipe/subversion/tests/repos/db/revs/3
iw/recipe/subversion/tests/repos/db/revs/4
iw/recipe/subversion/tests/repos/hooks/post-commit.tmpl
iw/recipe/subversion/tests/repos/hooks/post-lock.tmpl
iw/recipe/subversion/tests/repos/hooks/post-revprop-change.tmpl
iw/recipe/subversion/tests/repos/hooks/post-unlock.tmpl
iw/recipe/subversion/tests/repos/hooks/pre-commit.tmpl
iw/recipe/subversion/tests/repos/hooks/pre-lock.tmpl
iw/recipe/subversion/tests/repos/hooks/pre-revprop-change.tmpl
iw/recipe/subversion/tests/repos/hooks/pre-unlock.tmpl
iw/recipe/subversion/tests/repos/hooks/start-commit.tmpl
iw/recipe/subversion/tests/repos/locks/db-logs.lock
iw/recipe/subversion/tests/repos/locks/db.lock
