Metadata-Version: 1.0
Name: iw.recipe.subversion
Version: 0.3.1
Summary: ZC buildout recipe to checkout a dir from a svn repository and archive it in a folder
Home-page: http://plone.org/products/iw-recipes
Author: Ingeniweb
Author-email: support@ingeniweb.com
License: GPL
Platform: UNKNOWN
Classifier: Programming Language :: Python
Classifier: Topic :: Software Development :: Libraries :: Python Modules
